su/__init__.py
su/models.py
su/urls.py
su/urls.py.bak
su/views.py
django_switch_user-2.1.0.dist-info/AUTHORS
django_switch_user-2.1.0.dist-info/LICENSE
django_switch_user-2.1.0.dist-info/METADATA
django_switch_user-2.1.0.dist-info/WHEEL
django_switch_user-2.1.0.dist-info/top_level.txt
django_switch_user-2.1.0.dist-info/RECORD
