Metadata-Version: 2.1
Name: django-switch-user
Version: 2.1.0
Summary: Django Switch User allows you to assume the identity of another user.
Home-page: http://michaeltrier.com
Author: Michael Trier
Author-email: mtrier@gmail.com
License: MIT
Classifier: Development Status :: 4 - Beta
Classifier: Programming Language :: Python
License-File: LICENSE
License-File: AUTHORS
